<?xml version="1.0" encoding="UTF-8"?>
<databaseChangeLog xmlns="http://www.liquibase.org/xml/ns/dbchangelog" xmlns:xsi="http://www.w3.org/2001/XMLSchema-instance" xsi:schemaLocation="http://www.liquibase.org/xml/ns/dbchangelog          http://www.liquibase.org/xml/ns/dbchangelog/dbchangelog-3.1.xsd">
  <changeSet id="01" author="nikhil.shinde">
    <sql>
      CREATE EXTENSION IF NOT EXISTS "uuid-ossp";
    </sql>
    <createTable tableName="users" remarks="Table containing details of user">
      <column name="id" type="BIGINT" autoIncrement="true">
        <constraints nullable="false" unique="true" primaryKey="true" />
      </column>
      <column name="guid" type="uuid" defaultValue="uuid_generate_v4()">
        <constraints nullable="false" unique="true" />
      </column>
      <column name="user_name" type="varchar(20)">
        <constraints nullable="false"  unique="true"/>
      </column>
      <column name="password" type="varchar(200)">
        <constraints nullable="false" />
      </column>
      <column name="email" type="varchar(50)">
        <constraints nullable="false" unique="true"/>
      </column>
      <column name="created_at" type="datetime">
        <constraints nullable="false" />
      </column>
      <column name="updated_at" type="datetime">
        <constraints nullable="false" />
      </column>
      <column name="created_by" type="varchar(200)">
        <constraints nullable="false" />
      </column>
      <column name="updated_by" type="varchar(200)">
        <constraints nullable="false" />
      </column>
    </createTable>
  </changeSet>
</databaseChangeLog>